{"loss": 0.3381442433595657, "accuracy": 0.856, "timestamp": 1734200591, "checkpoint_dir_name": null, "done": false, "training_iteration": 1, "trial_id": "118aaf08", "date": "2024-12-14_18-23-11", "time_this_iter_s": 0.4681582450866699, "time_total_s": 0.4681582450866699, "pid": 98742, "hostname": "UNKNOWN", "node_ip": "127.0.0.1", "config": {"num_layers": 1, "hidden_units": 128, "lr": 0.01}, "time_since_restore": 0.4681582450866699, "iterations_since_restore": 1}
{"loss": 0.11007695707678795, "accuracy": 0.954, "timestamp": 1734200592, "checkpoint_dir_name": null, "done": true, "training_iteration": 2, "trial_id": "118aaf08", "date": "2024-12-14_18-23-12", "time_this_iter_s": 0.013103723526000977, "time_total_s": 0.4812619686126709, "pid": 98742, "hostname": "UNKNOWN", "node_ip": "127.0.0.1", "config": {"num_layers": 1, "hidden_units": 128, "lr": 0.01}, "time_since_restore": 0.4812619686126709, "iterations_since_restore": 2}
