{"loss": 0.565275375366211, "accuracy": 0.778, "timestamp": 1734199765, "checkpoint_dir_name": null, "done": false, "training_iteration": 1, "trial_id": "82200af1", "date": "2024-12-14_18-09-25", "time_this_iter_s": 0.45061182975769043, "time_total_s": 0.45061182975769043, "pid": 80158, "hostname": "UNKNOWN", "node_ip": "127.0.0.1", "config": {"num_layers": 1, "hidden_units": 32, "lr": 0.00388300134424263}, "time_since_restore": 0.45061182975769043, "iterations_since_restore": 1}
{"loss": 0.3373438675403595, "accuracy": 0.932, "timestamp": 1734199765, "checkpoint_dir_name": null, "done": false, "training_iteration": 2, "trial_id": "82200af1", "date": "2024-12-14_18-09-25", "time_this_iter_s": 0.010719060897827148, "time_total_s": 0.4613308906555176, "pid": 80158, "hostname": "UNKNOWN", "node_ip": "127.0.0.1", "config": {"num_layers": 1, "hidden_units": 32, "lr": 0.00388300134424263}, "time_since_restore": 0.4613308906555176, "iterations_since_restore": 2}
{"loss": 0.19145187622308732, "accuracy": 0.967, "timestamp": 1734199765, "checkpoint_dir_name": null, "done": false, "training_iteration": 3, "trial_id": "82200af1", "date": "2024-12-14_18-09-25", "time_this_iter_s": 0.010252714157104492, "time_total_s": 0.47158360481262207, "pid": 80158, "hostname": "UNKNOWN", "node_ip": "127.0.0.1", "config": {"num_layers": 1, "hidden_units": 32, "lr": 0.00388300134424263}, "time_since_restore": 0.47158360481262207, "iterations_since_restore": 3}
{"loss": 0.1257027941942215, "accuracy": 0.975, "timestamp": 1734199765, "checkpoint_dir_name": null, "done": false, "training_iteration": 4, "trial_id": "82200af1", "date": "2024-12-14_18-09-25", "time_this_iter_s": 0.009880781173706055, "time_total_s": 0.4814643859863281, "pid": 80158, "hostname": "UNKNOWN", "node_ip": "127.0.0.1", "config": {"num_layers": 1, "hidden_units": 32, "lr": 0.00388300134424263}, "time_since_restore": 0.4814643859863281, "iterations_since_restore": 4}
{"loss": 0.0933475774526596, "accuracy": 0.987, "timestamp": 1734199765, "checkpoint_dir_name": null, "done": true, "training_iteration": 5, "trial_id": "82200af1", "date": "2024-12-14_18-09-25", "time_this_iter_s": 0.00975489616394043, "time_total_s": 0.49121928215026855, "pid": 80158, "hostname": "UNKNOWN", "node_ip": "127.0.0.1", "config": {"num_layers": 1, "hidden_units": 32, "lr": 0.00388300134424263}, "time_since_restore": 0.49121928215026855, "iterations_since_restore": 5}
