{"loss": 0.35198742866516114, "accuracy": 0.84, "timestamp": 1734200631, "checkpoint_dir_name": null, "done": false, "training_iteration": 1, "trial_id": "a3b9e6b7", "date": "2024-12-14_18-23-51", "time_this_iter_s": 0.5562961101531982, "time_total_s": 0.5562961101531982, "pid": 99632, "hostname": "UNKNOWN", "node_ip": "127.0.0.1", "config": {"num_layers": 3, "hidden_units": 128, "lr": 0.01}, "time_since_restore": 0.5562961101531982, "iterations_since_restore": 1}
{"loss": 0.10904970336705447, "accuracy": 0.958, "timestamp": 1734200631, "checkpoint_dir_name": null, "done": true, "training_iteration": 2, "trial_id": "a3b9e6b7", "date": "2024-12-14_18-23-51", "time_this_iter_s": 0.019588232040405273, "time_total_s": 0.5758843421936035, "pid": 99632, "hostname": "UNKNOWN", "node_ip": "127.0.0.1", "config": {"num_layers": 3, "hidden_units": 128, "lr": 0.01}, "time_since_restore": 0.5758843421936035, "iterations_since_restore": 2}
